vansarah/__init__.py
vansarah/__main__.py
vansarah/custom_stft.py
vansarah/istftnet.py
vansarah/model.py
vansarah/modules.py
vansarah/pipeline.py
vansarah-1.0.2.dist-info/METADATA
vansarah-1.0.2.dist-info/WHEEL
vansarah-1.0.2.dist-info/entry_points.txt
vansarah-1.0.2.dist-info/licenses/LICENSE
vansarah-1.0.2.dist-info/RECORD
