Metadata-Version: 2.4
Name: vansarah
Version: 1.0.2
Summary: TTS
Project-URL: Homepage, https://github.com/mr-don88/vansarah
Project-URL: Repository, https://github.com/mr-don88/vansarah
Author-email: mr-don88 <donson.vietmold@gmail.com>
License:                                  Apache License
License-File: LICENSE
Classifier: License :: OSI Approved :: Apache Software License
Classifier: Operating System :: OS Independent
Classifier: Programming Language :: Python :: 3
Requires-Python: <3.14,>=3.10
Requires-Dist: gdown
Requires-Dist: huggingface-hub
Requires-Dist: loguru
Requires-Dist: numpy
Requires-Dist: quangdon[en]>=0.9.6
Requires-Dist: torch
Requires-Dist: transformers
